{"typ záznamu": "Archiválie", "signatura": "XI 5771", "heslo": "Praha-Staré Město - dům čp. 1", "druh": "negativ", "obsah": "Celkový pohled na východní průčelí Staroměstské radnice (dům čp. 1 na Starém Městě) na Staroměstském náměstí. Vpravo Krenův dům (čp. 936), v popředí Mariánský sloup.", "autor": "Bellmann-ateliér", "datace": "kol.1895", "zobrazeno": "61x", "xid": "B1FFDAABD0C011EABE1F74D435EEBE90", "rejstříkové záznamy": [], "scan_count": 0, "scan_indices": [], "scan_previews": [], "scan_zoomify_paths": [], "has_scans": false}