{"typ záznamu": "Archiválie", "signatura": "A 15899", "heslo": "Praha-Kobylisy - ulice Klapkova", "druh": "pozitiv", "obsah": "Průhled Klapkovou ulicí (Rudé armády) od křižovatky s Trojskou, Zenklovou a Nad Šutkou k severovýchodu. Zleva domy čp. 40, čp. 41, čp. 42, zprava dům čp. 26 v Kobylisích.", "autor": "Alexander, Antonín (1892-působnost do 1948)", "datace": "1.6.1944", "zobrazeno": "90x", "xid": "0b81096fe6a9476691a2429c9257ca2a", "rejstříkové záznamy": [{"typ": "Dílo", "obsah": "dům čp. 26 (Praha-Kobylisy)"}, {"typ": "Dílo", "obsah": "dům čp. 40 (Praha-Kobylisy)"}, {"typ": "Dílo", "obsah": "dům čp. 41 (Praha-Kobylisy)"}, {"typ": "Dílo", "obsah": "dům čp. 42 (Praha-Kobylisy)"}, {"typ": "Místo", "obsah": "Klapkova ulice"}, {"typ": "Místo", "obsah": "Kobylisy"}, {"typ": "Osoba", "obsah": "Alexander, Antonín (1892-působnost do 1948)"}], "scan_count": 0, "scan_indices": [], "scan_previews": [], "scan_zoomify_paths": [], "has_scans": false, "geolocation": {"name": "Klapkova 3/26", "label": "Adresa", "position": {"lon": 14.45611, "lat": 50.12408}, "bbox": [14.453303236797797, 50.12300189486454, 14.458917707323542, 50.125161648491], "type": "regional.address", "location": "Praha 8 - Kobylisy, Česko", "regionalStructure": [{"name": "3/26", "type": "regional.address"}, {"name": "Klapkova", "type": "regional.street"}, {"name": "Kobylisy", "type": "regional.municipality_part"}, {"name": "Praha 8", "type": "regional.municipality_part"}, {"name": "Praha", "type": "regional.municipality"}, {"name": "okres Hlavní město Praha", "type": "regional.region"}, {"name": "kraj Hlavní město Praha", "type": "regional.region"}, {"name": "Česko", "type": "regional.country", "isoCode": "CZ"}], "zip": "182 00", "endpoint": "geocode", "match_type": "cp", "query": "dům čp. 26 (Praha-Kobylisy)"}}