{"typ záznamu": "Archiválie", "signatura": "XI 1784", "heslo": "Praha-Josefov - ulice U Staré školy", "druh": "negativ", "obsah": "Pohled do ulice U Staré školy. Uprostřed dům čp. 156 v Josefově, část Španělské synagogy čp. 141 v Josefově vpravo.", "autor": "Kříženecký, Jan (1868-1921)", "datace": "30.10.1909", "zobrazeno": "7x", "xid": "229409f530c54923bc983933dda88ade", "rejstříkové záznamy": [{"typ": "Dílo", "obsah": "dům čp. 156 (Praha-Josefov)"}, {"typ": "Místo", "obsah": "Josefov"}, {"typ": "Místo", "obsah": "U staré školy"}, {"typ": "Osoba", "obsah": "Kříženecký, Jan (1868-1921)"}], "scan_count": 0, "scan_indices": [], "scan_previews": [], "scan_zoomify_paths": [], "has_scans": false, "geolocation": {"name": "Kaprova 14/13", "label": "Adresa", "position": {"lon": 14.41868, "lat": 50.08806}, "bbox": [14.415875279731184, 50.086978431620274, 14.421489750256928, 50.08913981019831], "type": "regional.address", "location": "Praha 1 - Josefov, Česko", "regionalStructure": [{"name": "14/13", "type": "regional.address"}, {"name": "Kaprova", "type": "regional.street"}, {"name": "Josefov", "type": "regional.municipality_part"}, {"name": "Praha 1", "type": "regional.municipality_part"}, {"name": "Praha", "type": "regional.municipality"}, {"name": "okres Hlavní město Praha", "type": "regional.region"}, {"name": "kraj Hlavní město Praha", "type": "regional.region"}, {"name": "Česko", "type": "regional.country", "isoCode": "CZ"}], "zip": "110 00", "endpoint": "geocode", "match_type": "fallback", "query": "dům čp. 156 (Praha-Josefov)"}}