{"typ záznamu": "Archiválie", "signatura": "I 9670", "druh": "pohlednice", "obsah": "Pohled na budovu nemocnice na Vinohradech (dům čp. 1150) - Všeobecná veřejná nemocnice Protektorátu Čechy a Morava na Král. Vinohradech.", "datace": "1939-1945", "zobrazeno": "57x", "xid": "4494BA13275211E287E86C626D41E503", "rejstříkové záznamy": [{"typ": "Dílo", "obsah": "dům čp. 1150 (Praha-Vinohrady)"}, {"typ": "Místo", "obsah": "Vinohrady"}, {"typ": "Osoba", "obsah": "nákladem Boženy Lukešové"}], "geolocation": {"name": "Šrobárova 1150/50", "label": "Adresa", "position": {"lon": 14.47543, "lat": 50.07572}, "type": "regional.address", "location": "Praha 10 - Vinohrady, Česko", "regionalStructure": [{"name": "1150/50", "type": "regional.address"}, {"name": "Šrobárova", "type": "regional.street"}, {"name": "Vinohrady", "type": "regional.municipality_part"}, {"name": "Praha 10", "type": "regional.municipality_part"}, {"name": "Praha", "type": "regional.municipality"}, {"name": "okres Hlavní město Praha", "type": "regional.region"}, {"name": "kraj Hlavní město Praha", "type": "regional.region"}, {"name": "Česko", "type": "regional.country", "isoCode": "CZ"}], "zip": "100 00", "endpoint": "geocode"}}