{"typ záznamu": "Archiválie", "signatura": "A 1277", "heslo": "Praha-Bohnice - dům čp. 138", "druh": "pozitiv", "obsah": "Pohled na dům čp. 138 na bývalé návsi ve starých Bohnicích (dnes na nároží ulic Bohnické a Ústavní). Čtvrtá část čtyřdílného panoramatu.", "autor": "Alexander, Antonín (1892-působnost do 1948)", "datace": "8.10.1924", "zobrazeno": "79x", "xid": "48EBE449212F11E8925674D435EEBE90", "rejstříkové záznamy": [{"typ": "Dílo", "obsah": "dům čp. 138 (Praha-Bohnice)"}, {"typ": "Místo", "obsah": "Bohnice"}, {"typ": "Místo", "obsah": "Bohnická ulice"}, {"typ": "Místo", "obsah": "Ústavní ulice"}, {"typ": "Osoba", "obsah": "Alexander, Antonín (1892-působnost do 1948)"}], "scan_count": 0, "scan_indices": [], "scan_previews": [], "scan_zoomify_paths": [], "has_scans": false, "geolocation": {"name": "Ústavní 138/1", "label": "Adresa", "position": {"lon": 14.41634, "lat": 50.13383}, "bbox": [14.413531746641082, 50.132750087509734, 14.41914621716683, 50.134909401266526], "type": "regional.address", "location": "Praha 8 - Bohnice, Česko", "regionalStructure": [{"name": "138/1", "type": "regional.address"}, {"name": "Ústavní", "type": "regional.street"}, {"name": "Bohnice", "type": "regional.municipality_part"}, {"name": "Praha 8", "type": "regional.municipality_part"}, {"name": "Praha", "type": "regional.municipality"}, {"name": "okres Hlavní město Praha", "type": "regional.region"}, {"name": "kraj Hlavní město Praha", "type": "regional.region"}, {"name": "Česko", "type": "regional.country", "isoCode": "CZ"}], "zip": "181 00", "endpoint": "geocode", "match_type": "cp", "query": "dům čp. 138 (Praha-Bohnice)"}}