{"typ záznamu": "Archiválie", "signatura": "Voj 127", "heslo": "Praha-Podolí - panorama", "druh": "pozitiv", "obsah": "Pohled z bastionu 36 vyšehradských hradeb k jihu na Podolí a vltavské údolí. V popředí přístav a přístavní hráz s dřevěnou budovou Yacht klubu (dům čp. 1148 v Podolí). V pozadí vlevo Podolské nábřeží a Veslařský ostrov. Vpravo smíchovský břeh. Součást panoramatu.", "autor": "Vojta, Tomáš (1885-1934)", "datace": "10.9.1923", "zobrazeno": "138x", "xid": "A10151A0612311E995BC74D435EEBE90", "rejstříkové záznamy": [{"typ": "Dílo", "obsah": "dům čp. 1148 (Praha-Podolí);Yacht klub"}, {"typ": "Dílo", "obsah": "dům čp. 157 (Praha-Podolí); nemocnice"}, {"typ": "Dílo", "obsah": "přístav (Praha-Podolí)"}, {"typ": "Místo", "obsah": "Podolí"}, {"typ": "Místo", "obsah": "Podolské nábřeží"}, {"typ": "Místo", "obsah": "Veslařský ostrov"}, {"typ": "Místo", "obsah": "Vltava"}, {"typ": "Osoba", "obsah": "Vojta, Tomáš (1885-1934)"}], "scan_count": 0, "scan_indices": [], "scan_previews": [], "scan_zoomify_paths": [], "has_scans": false, "geolocation": {"name": "Podolský přístav 1148/5", "label": "Adresa", "position": {"lon": 14.41735, "lat": 50.06113}, "bbox": [14.414540437149759, 50.06004881532142, 14.420154907675506, 50.06221140808645], "type": "regional.address", "location": "Praha 4 - Podolí, Česko", "regionalStructure": [{"name": "1148/5", "type": "regional.address"}, {"name": "Podolský přístav", "type": "regional.street"}, {"name": "Podolí", "type": "regional.municipality_part"}, {"name": "Praha 4", "type": "regional.municipality_part"}, {"name": "Praha", "type": "regional.municipality"}, {"name": "okres Hlavní město Praha", "type": "regional.region"}, {"name": "kraj Hlavní město Praha", "type": "regional.region"}, {"name": "Česko", "type": "regional.country", "isoCode": "CZ"}], "zip": "140 00", "endpoint": "geocode", "match_type": "cp", "query": "dům čp. 1148 (Praha-Podolí)"}}