{"typ záznamu": "Archiválie", "signatura": "VIII 287", "druh": "negativ", "obsah": "Pohled na Prašnou bránu a Obecní dům (dům čp. 1090 na Starém Městě). Vlevo část domu čp. 969 na Starém Městě.", "autor": "Eckert-ateliér", "datace": "25.4.1912", "zobrazeno": "96x", "xid": "A1187D16B67611DF820F00166F1163D4", "rejstříkové záznamy": [{"typ": "Dílo", "obsah": "dům čp. 1090 (Praha-Staré Město); Obecní dům"}, {"typ": "Dílo", "obsah": "dům čp. 969 (Praha-Staré Město); původní"}, {"typ": "Dílo", "obsah": "Prašná brána (Staré Město, Praha, Česko : stavba : 1475-)"}, {"typ": "Místo", "obsah": "náměstí Republiky"}, {"typ": "Místo", "obsah": "Staré Město (Praha)"}, {"typ": "Osoba", "obsah": "Eckert-ateliér"}], "geolocation": {"name": "náměstí Republiky 1090/5", "label": "Adresa", "position": {"lon": 14.42825, "lat": 50.08762}, "type": "regional.address", "location": "Praha 1 - Staré Město, Česko", "regionalStructure": [{"name": "1090/5", "type": "regional.address"}, {"name": "náměstí Republiky", "type": "regional.street"}, {"name": "Staré Město", "type": "regional.municipality_part"}, {"name": "Praha 1", "type": "regional.municipality_part"}, {"name": "Praha", "type": "regional.municipality"}, {"name": "okres Hlavní město Praha", "type": "regional.region"}, {"name": "kraj Hlavní město Praha", "type": "regional.region"}, {"name": "Česko", "type": "regional.country", "isoCode": "CZ"}], "zip": "110 00", "endpoint": "geocode"}}