{"typ záznamu": "Archiválie", "signatura": "XII 89", "heslo": "Praha-Hradčany - dům čp. 48", "druh": "negativ", "obsah": "Celkový pohled na Staré proboštství na 3. nádvoří Pražského hradu (dům čp. 48 na Hradčanech).", "autor": "Eckert, Jindřich (1833-1905)", "datace": "kol.1885", "zobrazeno": "31x", "xid": "EB59D1EC091611E0BDAE000C766D2371", "rejstříkové záznamy": [{"typ": "Dílo", "obsah": "dům čp. 48 (Praha-Hradčany); Staré proboštství"}, {"typ": "Dílo", "obsah": "katedrála svatého Víta (Hradčany, Praha, Česko : katedrála)"}, {"typ": "Dílo", "obsah": "Pražský hrad (Hradčany, Praha, Česko : stavba)"}, {"typ": "Místo", "obsah": "Hradčany"}, {"typ": "Osoba", "obsah": "Eckert, Jindřich (1833-1905)"}], "scan_count": 0, "scan_indices": [], "scan_previews": [], "scan_zoomify_paths": [], "has_scans": false, "geolocation": {"name": "Hrad III. nádvoří 48/2", "label": "Adresa", "position": {"lon": 14.39995, "lat": 50.09041}, "type": "regional.address", "location": "Praha 1 - Hradčany, Česko", "regionalStructure": [{"name": "48/2", "type": "regional.address"}, {"name": "Hrad III. nádvoří", "type": "regional.street"}, {"name": "Hradčany", "type": "regional.municipality_part"}, {"name": "Praha 1", "type": "regional.municipality_part"}, {"name": "Praha", "type": "regional.municipality"}, {"name": "okres Hlavní město Praha", "type": "regional.region"}, {"name": "kraj Hlavní město Praha", "type": "regional.region"}, {"name": "Česko", "type": "regional.country", "isoCode": "CZ"}], "zip": "119 00", "endpoint": "geocode", "match_type": "cp", "query": "dům čp. 48 (Praha-Hradčany)"}}