{"typ záznamu": "Archiválie", "signatura": "I 9058", "druh": "pozitiv", "obsah": "Panoramatický pohled na Hostivař z lomu jihozápadně nad cihelnou (domy čp. 279 a 533). Druhá část šestidílného panoramatu.", "autor": "Alexander, Antonín (1892-působnost do 1948)", "datace": "9.6.1930", "zobrazeno": "91x", "xid": "A0C4FC74B67611DF820F00166F1163D4", "rejstříkové záznamy": [{"typ": "Dílo", "obsah": "dům čp. 279 (Praha-Hostivař); cihelna"}, {"typ": "Dílo", "obsah": "dům čp. 533 (Praha-Hostivař); cihelna"}, {"typ": "Místo", "obsah": "Hostivař"}, {"typ": "Osoba", "obsah": "Alexander, Antonín (1892-působnost do 1948)"}, {"typ": "Věc. objekt", "obsah": "cihelny (korporace)"}, {"typ": "Věc. objekt", "obsah": "panoramatické pohledy"}]}