{"typ záznamu": "Archiválie", "signatura": "I 9704", "heslo": "Praha-Žižkov - Židovský hřbitov", "druh": "pozitiv", "obsah": "Pohled do Židovského hřbitova na Žižkově (v místech dnešních Mahlerových sadů).", "autor": "Alexander, Antonín (1892-působnost do 1948)", "datace": "14.4.1933", "zobrazeno": "153x", "xid": "0C62D795863D11E294336C626D41E503", "rejstříkové záznamy": [{"typ": "Dílo", "obsah": "Starý olšanský židovský hřbitov (Žižkov, Praha, Česko : židovský hřbitov : 1680-)"}, {"typ": "Místo", "obsah": "Mahlerovy sady"}, {"typ": "Místo", "obsah": "Žižkov"}, {"typ": "Osoba", "obsah": "Alexander, Antonín (1892-působnost do 1948)"}, {"typ": "Věc. objekt", "obsah": "hřbitovy (areály)"}], "scan_count": 0, "scan_indices": [], "scan_previews": [], "scan_zoomify_paths": [], "has_scans": false}