{"typ záznamu": "Archiválie", "signatura": "VIII 1169", "heslo": "Praha-Staré Město - kostel sv. Klimenta", "druh": "negativ", "obsah": "Pohled do interiéru kostela sv. Klimenta v Klementinu (dům čp. 190, 1040) na Starém Městě - strop.", "autor": "Eckert-ateliér", "datace": "6.11.1911", "zobrazeno": "40x", "xid": "0F1F3C136AC811E295C66C626D41E503", "rejstříkové záznamy": [{"typ": "Dílo", "obsah": "Klementinum (Staré Město, Praha, Česko : stavba)"}, {"typ": "Dílo", "obsah": "kostel sv. Klimenta v Klementinu (Praha-Staré Město)"}, {"typ": "Místo", "obsah": "Karlova ulice"}, {"typ": "Místo", "obsah": "Staré Město"}, {"typ": "Osoba", "obsah": "Eckert-ateliér"}], "scan_count": 0, "scan_indices": [], "scan_previews": [], "scan_zoomify_paths": [], "has_scans": false}