{"typ záznamu": "Archiválie", "signatura": "V 19/20", "heslo": "Praha-Nové Město - nádraží", "druh": "pozitiv", "obsah": "Pohled ze svahu Vítkova na vnější část nádraží Rakouské společnosti státní dráhy (dnes Masarykovo nádraží - dům čp. 1014 na Novém Městě).", "autor": "anonym", "datace": "kol.1870", "zobrazeno": "173x", "xid": "10E644DA21F311E8B26274D435EEBE90", "rejstříkové záznamy": [{"typ": "Dílo", "obsah": "Masarykovo nádraží (Nové Město, Praha, Česko : nádraží : 1845-)"}, {"typ": "Místo", "obsah": "Nové Město"}, {"typ": "Místo", "obsah": "Staré Město"}, {"typ": "Osoba", "obsah": "anonym"}], "scan_count": 0, "scan_indices": [], "scan_previews": [], "scan_zoomify_paths": [], "has_scans": false}