{"typ záznamu": "Archiválie", "signatura": "XII 1339", "heslo": "Praha-Nové Město - dům čp. 56", "druh": "negativ", "obsah": "Pohled na dům čp. 56 (německé dívčí lyceum) na nároží ulic Vladislavovy a Charvátovy na Novém Městě.", "autor": "Eckert-ateliér", "datace": "kol.1910", "zobrazeno": "86x", "xid": "1637E8CE663111E2A1036C626D41E503", "rejstříkové záznamy": [{"typ": "Dílo", "obsah": "dům čp. 56 (Praha-Nové Město); škola"}, {"typ": "Místo", "obsah": "Charvátova ulice"}, {"typ": "Místo", "obsah": "Nové Město"}, {"typ": "Místo", "obsah": "Vladislavova ulice"}, {"typ": "Osoba", "obsah": "Eckert-ateliér"}], "scan_count": 0, "scan_indices": [], "scan_previews": [], "scan_zoomify_paths": [], "has_scans": false}