{"typ záznamu": "Archiválie", "signatura": "VIII 1632", "heslo": "Hrubá Skála - skály", "druh": "negativ", "obsah": "Pohled na pískovcové skály u Hrubé Skály. V pozadí zříceniny hradu Trosky.", "autor": "Eckert, Jindřich (1833-1905)", "datace": "1894", "zobrazeno": "16x", "xid": "23AF938B9D0811E2BF2E525400E46D25", "rejstříkové záznamy": [{"typ": "Dílo", "obsah": "Trosky (Tachov, Troskovice, Semily, Česko : hrad)"}, {"typ": "Místo", "obsah": "Hrubá Skála"}, {"typ": "Místo", "obsah": "Trosky"}, {"typ": "Osoba", "obsah": "Eckert, Jindřich (1833-1905)"}], "scan_count": 0, "scan_indices": [], "scan_previews": [], "scan_zoomify_paths": [], "has_scans": false}