{"typ záznamu": "Archiválie", "signatura": "XI 456", "heslo": "Praha-Malá Strana - Kampa", "druh": "negativ", "obsah": "Partie z Odkolkovské zahrady na Kampě na Malé Straně.", "autor": "Kříženecký, Jan (1868-1921)", "datace": "16.10.1907", "zobrazeno": "81x", "xid": "3933C02DE03211E3A3D40024BE7CD9AC", "rejstříkové záznamy": [{"typ": "Místo", "obsah": "Kampa"}, {"typ": "Místo", "obsah": "Malá Strana"}, {"typ": "Osoba", "obsah": "Kříženecký, Jan (1868-1921)"}], "scan_count": 0, "scan_indices": [], "scan_previews": [], "scan_zoomify_paths": [], "has_scans": false}