{"typ záznamu": "Archiválie", "signatura": "XI 90", "heslo": "Kojetice - kostel sv. Víta", "druh": "negativ", "obsah": "Pohled do interiéru kostela sv. Víta v Kojeticích.", "autor": "Kříženecký, Jan (1868-1921)", "datace": "leden 1906", "zobrazeno": "18x", "xid": "40981723A48011E3BEEB406186009F3A", "rejstříkové záznamy": [{"typ": "Dílo", "obsah": "kostel svatého Víta (Kojetice, Mělník, Česko : kostel)"}, {"typ": "Místo", "obsah": "Kojetice"}, {"typ": "Osoba", "obsah": "Kříženecký, Jan (1868-1921)"}], "scan_count": 0, "scan_indices": [], "scan_previews": [], "scan_zoomify_paths": [], "has_scans": false}