{"typ záznamu": "Archiválie", "signatura": "XII 429", "heslo": "Svatojánské proudy", "druh": "negativ", "obsah": "Pohled na Ferdinandův pamětní sloup ve vltavském údolí \"Svatojánské proudy\".", "autor": "Eckert, Jindřich (1833-1905)", "datace": "kol.1885", "zobrazeno": "39x", "xid": "4A39FBCC362711E1BECE000C766D2371", "rejstříkové záznamy": [{"typ": "Místo", "obsah": "Svatojánské proudy"}, {"typ": "Místo", "obsah": "Vltava"}, {"typ": "Osoba", "obsah": "Eckert, Jindřich (1833-1905)"}], "scan_count": 0, "scan_indices": [], "scan_previews": [], "scan_zoomify_paths": [], "has_scans": false}