{"typ záznamu": "Archiválie", "signatura": "A 876", "heslo": "Praha-Bubeneč - zdymadlo", "druh": "pozitiv", "obsah": "Panoramatický pohled na zdymadlo z hráze plavebního kanálu na Císařském ostrově v Bubenči. Druhá část dvoudílného panoramatu A 876 - A 876.", "autor": "Alexander, Antonín (1892-působnost do 1948)", "datace": "10.6.1924", "zobrazeno": "15x", "xid": "52a59ae0482246eaa33635c92075b146", "rejstříkové záznamy": [{"typ": "Dílo", "obsah": "zdymadlo (Praha-Bubeneč)"}, {"typ": "Místo", "obsah": "Bubeneč"}, {"typ": "Místo", "obsah": "Císařský ostrov"}, {"typ": "Místo", "obsah": "Dejvice"}, {"typ": "Místo", "obsah": "Podbaba"}, {"typ": "Místo", "obsah": "Vltava"}, {"typ": "Osoba", "obsah": "Alexander, Antonín (1892-působnost do 1948)"}], "scan_count": 0, "scan_indices": [], "scan_previews": [], "scan_zoomify_paths": [], "has_scans": false}