{"typ záznamu": "Archiválie", "signatura": "I 11867", "heslo": "Praha - Vltava - splavnění", "druh": "pozitiv", "obsah": "Pohled na stavbu špičky ostrova Štvanice. V pozadí provizorní dřevěný a nedokončená železná část Hlávkova mostu.", "datace": "16.10.1909", "zobrazeno": "55x", "xid": "54FE7D47648711E6A554000C76270B94", "rejstříkové záznamy": [{"typ": "Dílo", "obsah": "Hlávkův most (Praha, Česko : most : 1911-)"}, {"typ": "Dílo", "obsah": "provizorní dřevěný most (dnes zde Hlávkův)"}, {"typ": "Místo", "obsah": "Holešovice"}, {"typ": "Místo", "obsah": "Štvanice"}, {"typ": "Místo", "obsah": "Vltava"}], "scan_count": 0, "scan_indices": [], "scan_previews": [], "scan_zoomify_paths": [], "has_scans": false}