{"typ záznamu": "Archiválie", "signatura": "I 12955", "heslo": "Svoboda, Adolf - primátor", "druh": "pozitiv", "obsah": "Primátor Adolf Svoboda ve své kanceláři.", "datace": "kol.1960", "zobrazeno": "24x", "xid": "582f81526c364bc6844763e746e97266", "rejstříkové záznamy": [{"typ": "Dílo", "obsah": "Letiště Václava Havla Praha (Ruzyně, Praha, Česko : stavba)"}, {"typ": "Místo", "obsah": "Ruzyně"}, {"typ": "Osoba", "obsah": "Parbus, Bohuslav"}, {"typ": "Osoba", "obsah": "Svoboda, Adolf (1900-1969)"}], "scan_count": 0, "scan_indices": [], "scan_previews": [], "scan_zoomify_paths": [], "has_scans": false}