{"typ záznamu": "Archiválie", "signatura": "X 3281", "heslo": "Praha - pražské typy", "druh": "negativ", "obsah": "Typy pražské - nosiči s košatinou ve staroměstském obecním dvoře.", "datace": "[1856-2014]", "poznámka": "Datace neznámá. Za účelem vyhledávání byla nastavena na časový rozsah celé sbírky.", "zobrazeno": "31x", "xid": "5830EF9CBC7611E28FB36C626D41E503", "rejstříkové záznamy": [{"typ": "Věc. objekt", "obsah": "pražské typy"}], "scan_count": 0, "scan_indices": [], "scan_previews": [], "scan_zoomify_paths": [], "has_scans": false}