{"typ záznamu": "Archiválie", "signatura": "I 11401", "heslo": "Praha-Břevnov - Markétská ulice", "druh": "pozitiv", "obsah": "Pohled do Markétské ulice s domy čp. 2 a čp. 3 v Břevnově (jižní průčelí).", "autor": "Alexander, Antonín (1892-působnost do 1948)", "datace": "3.9.1943", "zobrazeno": "60x", "xid": "5C9FE6BFB61311E58B3BD4BED94BB14D", "rejstříkové záznamy": [{"typ": "Dílo", "obsah": "dům čp. 2 / BŘEVNOV"}, {"typ": "Dílo", "obsah": "dům čp. 3 / BŘEVNOV"}, {"typ": "Místo", "obsah": "Břevnov"}, {"typ": "Místo", "obsah": "Markétská"}, {"typ": "Osoba", "obsah": "Alexander, Antonín (1892-působnost do 1948)"}], "scan_count": 0, "scan_indices": [], "scan_previews": [], "scan_zoomify_paths": [], "has_scans": false}