{"typ záznamu": "Archiválie", "signatura": "VIII 1453", "heslo": "Praha-Vysočany - mlékárna", "druh": "negativ", "obsah": "Pohled do dvora parní mlékárny ve Vysočanech - dům čp. 26 v Palackého ulici (dnes Freyova).", "autor": "Eckert, Jindřich (1833-1905)", "datace": "kol.1900", "zobrazeno": "127x", "xid": "644D96FC908E11E2BF26525400E46D25", "rejstříkové záznamy": [{"typ": "Dílo", "obsah": "dům čp. 26 (Praha-Vysočany); mlékárna"}, {"typ": "Místo", "obsah": "Freyova ulice"}, {"typ": "Místo", "obsah": "Vysočany"}, {"typ": "Osoba", "obsah": "Eckert, Jindřich (1833-1905)"}], "scan_count": 0, "scan_indices": [], "scan_previews": [], "scan_zoomify_paths": [], "has_scans": false}