{"typ záznamu": "Archiválie", "signatura": "I 11640", "heslo": "Praha - Vltava - splavnění", "druh": "pozitiv", "obsah": "Pohled na stavbu plavení komory u ostrova Štvanice. V pozadí nedokončená železná část Hlávkova mostu a provizorní dřevěný most (Hlávkův).", "datace": "23.9.1909", "zobrazeno": "79x", "xid": "65B211C0F75011E5A524000C76270B94", "rejstříkové záznamy": [{"typ": "Dílo", "obsah": "Hlávkův most (Praha, Česko : most : 1911-)"}, {"typ": "Dílo", "obsah": "provizorní dřevěný most (dnes zde Hlávkův)"}, {"typ": "Místo", "obsah": "Holešovice"}, {"typ": "Místo", "obsah": "Štvanice"}, {"typ": "Místo", "obsah": "Vltava"}, {"typ": "Věc. objekt", "obsah": "plavební komory"}], "scan_count": 0, "scan_indices": [], "scan_previews": [], "scan_zoomify_paths": [], "has_scans": false}