{"typ záznamu": "Archiválie", "signatura": "VIII 1589", "heslo": "Klášterec nad Ohří - železniční most", "druh": "negativ", "obsah": "Pohled na železniční most v Klášterci nad Ohří. V pozadí zámek.", "autor": "Eckert", "datace": "[1863-1945]", "poznámka": "Datace neznámá. Za účelem vyhledávání byla nastavena na časový rozsah celé sbírky.", "zobrazeno": "114x", "xid": "69BEB19196E211E2BF2B525400E46D25", "rejstříkové záznamy": [{"typ": "Dílo", "obsah": "Klášterec nad Ohří (Klášterec nad Ohří, Klášterec nad Ohří, Chomutov, Česko : zámek)"}, {"typ": "Dílo", "obsah": "železniční most (Klášterec nad Ohří)"}, {"typ": "Místo", "obsah": "Klášterec nad Ohří"}, {"typ": "Místo", "obsah": "Ohře"}, {"typ": "Osoba", "obsah": "Eckert"}], "scan_count": 0, "scan_indices": [], "scan_previews": [], "scan_zoomify_paths": [], "has_scans": false}