{"typ záznamu": "Archiválie", "signatura": "I 11753", "heslo": "Praha - Vltava - splavnění", "druh": "pozitiv", "obsah": "Pohled na stavbu špičky ostrova Štvanice. V pozadí most císaře Františka Josefa I.", "datace": "14.12.1908", "zobrazeno": "79x", "xid": "70691C0753D811E6A54D000C76270B94", "rejstříkové záznamy": [{"typ": "Dílo", "obsah": "most císaře Františka Josefa I. (Praha, Česko : most : 1868-1947)"}, {"typ": "Místo", "obsah": "Holešovice"}, {"typ": "Místo", "obsah": "Štvanice"}, {"typ": "Místo", "obsah": "Vltava"}], "scan_count": 0, "scan_indices": [], "scan_previews": [], "scan_zoomify_paths": [], "has_scans": false}