{"typ záznamu": "Archiválie", "signatura": "V 2/11", "heslo": "Praha-Staré Město - dům čp. 847", "druh": "pozitiv", "obsah": "Celkový pohled na kostel sv. Šimona a Judy na nároží ulic Dušní a U Milosrdných na Starém Městě. Vpravo klášter milosrdných bratří (dům čp. 847).", "autor": "Klíma, Alois, Ing. (1873-1955)", "datace": "1908", "zobrazeno": "72x", "xid": "74031F149A7411E4A736406186009F3A", "rejstříkové záznamy": [{"typ": "Dílo", "obsah": "dům čp. 847 (Staré Město, Praha, Česko : klášter)"}, {"typ": "Dílo", "obsah": "kostel sv. Šimona a Judy (Praha-Staré Město)"}, {"typ": "Místo", "obsah": "Staré Město"}, {"typ": "Místo", "obsah": "U milosrdných"}, {"typ": "Osoba", "obsah": "Klíma, Alois, Ing. (1873-1955)"}], "scan_count": 0, "scan_indices": [], "scan_previews": [], "scan_zoomify_paths": [], "has_scans": false}