{"typ záznamu": "Archiválie", "signatura": "A 3380", "heslo": "Praha-Malá Chuchle - panorama", "druh": "pozitiv", "obsah": "Pohled ze stráně nad Malou Chuchlí na vltavské údolí. V popředí železniční trať s nádražím v Malé Chuchli, Vltava. Za řekou vlevo Modřany. Vpravo v pozadí Velká Chuchle. Součást panoramatu.", "autor": "Alexander, Antonín (1892-působnost do 1948)", "datace": "17.6.1927", "zobrazeno": "87x", "xid": "8047E5E5035A11E7A51174D435EEBE90", "rejstříkové záznamy": [{"typ": "Osoba", "obsah": "Alexander, Antonín (1892-působnost do 1948)"}], "scan_count": 0, "scan_indices": [], "scan_previews": [], "scan_zoomify_paths": [], "has_scans": false}