{"typ záznamu": "Archiválie", "signatura": "XII 533", "heslo": "Orlík - hrad", "druh": "negativ", "obsah": "Pohled na hrad Orlík - severní strana.", "autor": "Eckert-ateliér", "datace": "[1863-1945]", "poznámka": "Datace neznámá. Za účelem vyhledávání byla nastavena na časový rozsah celé sbírky.", "zobrazeno": "15x", "xid": "8249B7E292DD11E193C36C626D41E503", "rejstříkové záznamy": [{"typ": "Dílo", "obsah": "Orlík (Orlík nad Vltavou, Orlík nad Vltavou, Písek, Česko : zámek)"}, {"typ": "Místo", "obsah": "Orlík"}, {"typ": "Osoba", "obsah": "Eckert-ateliér"}], "scan_count": 0, "scan_indices": [], "scan_previews": [], "scan_zoomify_paths": [], "has_scans": false}