{"typ záznamu": "Archiválie", "signatura": "A 15854", "heslo": "Praha-Kobylisy - ulice Na Pěšinách", "druh": "pozitiv", "obsah": "Průhled ulicí Na Pěšinách s domy čp. 34, 31, 366, 365 (vlevo) a s domem čp. 138 (vpravo) v Kobylisích.", "autor": "Alexander, Antonín (1892-působnost do 1948)", "datace": "31.5.1944", "zobrazeno": "81x", "xid": "93874C2D365A11E7B9CE406186009F3A", "rejstříkové záznamy": [{"typ": "Dílo", "obsah": "dům čp. 138 (Praha-Kobylisy)"}, {"typ": "Dílo", "obsah": "dům čp. 31 (Praha-Kobylisy)"}, {"typ": "Dílo", "obsah": "dům čp. 34 (Praha-Kobylisy)"}, {"typ": "Dílo", "obsah": "dům čp. 365 (Praha-Kobylisy)"}, {"typ": "Dílo", "obsah": "dům čp. 366 (Praha-Kobylisy)"}, {"typ": "Místo", "obsah": "Kobylisy"}, {"typ": "Místo", "obsah": "Na Pěšinách"}, {"typ": "Osoba", "obsah": "Alexander, Antonín (1892-působnost do 1948)"}], "scan_count": 0, "scan_indices": [], "scan_previews": [], "scan_zoomify_paths": [], "has_scans": false}