{"typ záznamu": "Archiválie", "signatura": "XII 139", "heslo": "Praha-Bubeneč - obora Královská (Stromovka)", "druh": "negativ", "obsah": "Pohled do Královské obory (Stromovky). V pozadí Místodržitelský letohrádek (dům čp. 56 v Bubenči).", "autor": "Eckert, Jindřich (1833-1905)", "datace": "kol.1885", "zobrazeno": "63x", "xid": "948E36C923B311E0BDC7000C766D2371", "rejstříkové záznamy": [{"typ": "Dílo", "obsah": "dům čp. 56 (Praha-Bubeneč); Místodržitelský letohrádek"}, {"typ": "Místo", "obsah": "Bubeneč"}, {"typ": "Místo", "obsah": "Stromovka"}, {"typ": "Osoba", "obsah": "Eckert, Jindřich (1833-1905)"}], "scan_count": 0, "scan_indices": [], "scan_previews": [], "scan_zoomify_paths": [], "has_scans": false}