{"typ záznamu": "Archiválie", "signatura": "VIII 1478", "heslo": "Praha-Smíchov - dům čp. 737", "druh": "negativ", "obsah": "Pohled do interiéru budovy Ústavu pro zaopatřování slepců Francisco Josephinum (dům čp. 737 na Smíchově - Palata) - kuchyně.", "autor": "Eckert, Jindřich (1833-1905)", "datace": "1893", "zobrazeno": "50x", "xid": "94BF0104922D11E2BF28525400E46D25", "rejstříkové záznamy": [{"typ": "Dílo", "obsah": "dům čp. 737 (Praha-Smíchov); Palata"}, {"typ": "Místo", "obsah": "Smíchov"}, {"typ": "Osoba", "obsah": "Eckert, Jindřich (1833-1905)"}], "scan_count": 0, "scan_indices": [], "scan_previews": [], "scan_zoomify_paths": [], "has_scans": false}