{"typ záznamu": "Archiválie", "signatura": "I 306", "heslo": "Praha-Staré Město - Mariánský sloup", "druh": "pohlednice", "obsah": "Pohled na stržený mariánský sloup na Staroměstském náměstí.", "datace": "3.11.1918", "zobrazeno": "268x", "xid": "A0C4FCDCB67611DF820F00166F1163D4", "rejstříkové záznamy": [{"typ": "Dílo", "obsah": "Mariánský sloup na Staroměstském náměstí (Jan Jiří Bendl : Staré Město, Praha, Česko : 1650-1918)"}, {"typ": "Místo", "obsah": "Staré Město"}, {"typ": "Místo", "obsah": "Staroměstské náměstí"}, {"typ": "Osoba", "obsah": "Nakladatelství Nová Grafika, Praha, Celetná 4"}], "scan_count": 0, "scan_indices": [], "scan_previews": [], "scan_zoomify_paths": [], "has_scans": false}