{"typ záznamu": "Archiválie", "signatura": "II 525", "heslo": "Praha-Staré Město - dům čp. 2", "druh": "pozitiv", "obsah": "Pohled na hlavní průčelí budovy Magistrátu hlavního města Prahy (dům čp. 2) na Starém Městě na Mariánském náměstí.", "autor": "Vojta, Tomáš (1885-1934)", "datace": "1914", "zobrazeno": "30x", "xid": "A0C4FE8FB67611DF820F00166F1163D4", "rejstříkové záznamy": [{"typ": "Dílo", "obsah": "dům čp. 2 (Praha-Staré Město); Nová radnice"}, {"typ": "Místo", "obsah": "Mariánské náměstí"}, {"typ": "Místo", "obsah": "Staré Město"}, {"typ": "Osoba", "obsah": "Vojta, Tomáš (1885-1934)"}], "scan_count": 0, "scan_indices": [], "scan_previews": [], "scan_zoomify_paths": [], "has_scans": false}