{"typ záznamu": "Archiválie", "signatura": "I 1740", "heslo": "Praha-Hloubětín - panorama", "druh": "pozitiv", "obsah": "Panoramatický pohled ze stráně Hlohovce z cesty nad osadou V Chaloupkách na Hloubětín.", "autor": "Alexander, Antonín (1892-působnost do 1948)", "datace": "28.9.1927", "zobrazeno": "93x", "xid": "A0C4FAACB67611DF820F00166F1163D4", "rejstříkové záznamy": [{"typ": "Místo", "obsah": "Hloubětín"}, {"typ": "Místo", "obsah": "V Chaloupkách"}, {"typ": "Osoba", "obsah": "Alexander, Antonín (1892-působnost do 1948)"}], "scan_count": 0, "scan_indices": [], "scan_previews": [], "scan_zoomify_paths": [], "has_scans": false}