{"typ záznamu": "Archiválie", "signatura": "II 216", "heslo": "Praha-Nové Město - dům čp. 223", "druh": "pozitiv", "obsah": "Pohled z mostu Františka I. (Legií) na na Národní divadlo (dům čp. 223 na Novém Městě). Vlevo část domu čp. 1012 na Starém Městě (kavárna Slavia).", "autor": "Kříženecký, Jan (1868-1921)", "datace": "26.4.1914", "zobrazeno": "176x", "xid": "A0C4F66BB67611DF820F00166F1163D4", "rejstříkové záznamy": [{"typ": "Dílo", "obsah": "dům čp. 1012 (Praha-Staré Město)"}, {"typ": "Dílo", "obsah": "most Legií (Praha, Česko : most : 1901-)"}, {"typ": "Dílo", "obsah": "Národní divadlo (Nové Město, Praha, Česko : divadlo : 1881-)"}, {"typ": "Místo", "obsah": "Masarykovo nábřeží"}, {"typ": "Místo", "obsah": "Národní třída"}, {"typ": "Místo", "obsah": "Nové Město"}, {"typ": "Místo", "obsah": "Smetanovo nábřeží"}, {"typ": "Místo", "obsah": "Staré Město"}, {"typ": "Místo", "obsah": "Vltava"}, {"typ": "Osoba", "obsah": "Kříženecký, Jan (1868-1921)"}, {"typ": "Věc. objekt", "obsah": "veřejná osvětlení (komunální služba)"}], "scan_count": 0, "scan_indices": [], "scan_previews": [], "scan_zoomify_paths": [], "has_scans": false}