{"typ záznamu": "Archiválie", "signatura": "II 21", "heslo": "Praha-Nové Město - dům čp. 791", "druh": "pozitiv", "obsah": "Pohled do dvora domu U Lhotků na Václavském náměstí čp. 791 na Novém Městě.", "autor": "Kříženecký, Jan (1868-1921)", "datace": "7.7.1913", "zobrazeno": "102x", "xid": "A0C4F64EB67611DF820F00166F1163D4", "rejstříkové záznamy": [{"typ": "Dílo", "obsah": "dům čp. 791 (Praha-Nové Město); původní, U Lhotků"}, {"typ": "Místo", "obsah": "Nové Město"}, {"typ": "Místo", "obsah": "Václavské náměstí"}, {"typ": "Osoba", "obsah": "Kříženecký, Jan (1868-1921)"}], "scan_count": 0, "scan_indices": [], "scan_previews": [], "scan_zoomify_paths": [], "has_scans": false}