{"typ záznamu": "Archiválie", "signatura": "VIII 688", "heslo": "Praha-Staré Město - dům čp. 190, 1040", "druh": "negativ", "obsah": "Pohled do interiéru Klementina (dům čp. 190, 1040) na Starém Městě - nově zřízené oratorium.", "autor": "Eckert-ateliér", "datace": "18.6.1909", "zobrazeno": "40x", "xid": "A0C50422B67611DF820F00166F1163D4", "rejstříkové záznamy": [{"typ": "Dílo", "obsah": "Klementinum (Staré Město, Praha, Česko : stavba)"}, {"typ": "Místo", "obsah": "Staré Město"}, {"typ": "Osoba", "obsah": "Eckert-ateliér"}], "scan_count": 0, "scan_indices": [], "scan_previews": [], "scan_zoomify_paths": [], "has_scans": false}