{"typ záznamu": "Archiválie", "signatura": "VIII 213", "heslo": "Praha-Staré Město - Staroměstské náměstí", "druh": "negativ", "obsah": "Pohled na severní stranu Staroměstského náměstí s domy (zleva) čp. 930, 929 a 928 (při bourání) na Starém Městě.", "autor": "Eckert, Jindřich (1833-1905)", "datace": "1897", "zobrazeno": "43x", "xid": "A0C516DAB67611DF820F00166F1163D4", "rejstříkové záznamy": [{"typ": "Dílo", "obsah": "dům čp. 928 (Praha-Staré Město)"}, {"typ": "Dílo", "obsah": "dům čp. 929 (Praha-Staré Město)"}, {"typ": "Dílo", "obsah": "dům čp. 930 (Praha-Staré Město)"}, {"typ": "Místo", "obsah": "Staré Město"}, {"typ": "Místo", "obsah": "Staroměstské náměstí"}, {"typ": "Osoba", "obsah": "Eckert, Jindřich (1833-1905)"}, {"typ": "Věc. objekt", "obsah": "Asanace"}], "scan_count": 0, "scan_indices": [], "scan_previews": [], "scan_zoomify_paths": [], "has_scans": false}