{"typ záznamu": "Archiválie", "signatura": "I 9119", "heslo": "Praha-Hradčany - dům čp. 104", "druh": "pozitiv", "obsah": "Pohled do Loretánské ulice s domem čp. 104 (Vrbnovský palác - Hradčanský ústav slepců) s podloubím. Vlevo dům čp. 103 na Hradčanech.", "autor": "Klíma, Alois, Ing. (1873-1955)", "datace": "23.9.1907", "zobrazeno": "64x", "xid": "A0C51590B67611DF820F00166F1163D4", "rejstříkové záznamy": [{"typ": "Dílo", "obsah": "dům čp. 103 (Praha-Hradčany)"}, {"typ": "Dílo", "obsah": "dům čp. 104 (Praha-Hradčany); Vrbnovský palác"}, {"typ": "Místo", "obsah": "Hradčany"}, {"typ": "Místo", "obsah": "Loretánská"}, {"typ": "Osoba", "obsah": "Klíma, Alois, Ing. (1873-1955)"}], "scan_count": 0, "scan_indices": [], "scan_previews": [], "scan_zoomify_paths": [], "has_scans": false}