{"typ záznamu": "Archiválie", "signatura": "I 1549", "heslo": "Praha-Malá Chuchle - ulice V lázních", "druh": "pozitiv", "obsah": "Pohled do ulice V lázních s lázeňskými domy (zleva) čp. 42, 44, 45, 43.", "autor": "Alexander, Antonín (1892-působnost do 1948)", "datace": "25.3.1942", "zobrazeno": "45x", "xid": "A0C51B05B67611DF820F00166F1163D4", "rejstříkové záznamy": [{"typ": "Dílo", "obsah": "dům čp. 42 (Praha-Malá Chuchle)"}, {"typ": "Dílo", "obsah": "dům čp. 43 (Praha-Malá Chuchle)"}, {"typ": "Dílo", "obsah": "dům čp. 44 (Praha-Malá Chuchle)"}, {"typ": "Dílo", "obsah": "dům čp. 45 (Praha-Malá Chuchle)"}, {"typ": "Místo", "obsah": "Malá Chuchle"}, {"typ": "Místo", "obsah": "ulice V lázních"}, {"typ": "Osoba", "obsah": "Alexander, Antonín (1892-působnost do 1948)"}], "scan_count": 0, "scan_indices": [], "scan_previews": [], "scan_zoomify_paths": [], "has_scans": false}