{"typ záznamu": "Archiválie", "signatura": "VI 23/10", "heslo": "Praha-Malá Strana - dům čp. 381", "druh": "pozitiv", "obsah": "Pohled na portál domu čp. 381 v Karmelitské ulici na Malé Straně.", "datace": "kol.1905", "zobrazeno": "22x", "xid": "A118873FB67611DF820F00166F1163D4", "rejstříkové záznamy": [{"typ": "Dílo", "obsah": "dům čp. 381 (Praha-Malá Strana); Bergenthalův"}, {"typ": "Místo", "obsah": "Karmelitská"}, {"typ": "Místo", "obsah": "Malá Strana"}], "scan_count": 0, "scan_indices": [], "scan_previews": [], "scan_zoomify_paths": [], "has_scans": false}