{"typ záznamu": "Archiválie", "signatura": "II 938", "heslo": "Praha-Hradčany - Pražský hrad", "druh": "pozitiv", "obsah": "Pohled na stavební průzkum jižních zahrad na Pražském hradě před úpravami Josipa Plečnika - západní část Rajské zahrady.", "datace": "1920-1922", "zobrazeno": "43x", "xid": "A1187D88B67611DF820F00166F1163D4", "rejstříkové záznamy": [{"typ": "Dílo", "obsah": "Pražský hrad (Hradčany, Praha, Česko : stavba)"}, {"typ": "Místo", "obsah": "Hradčany"}], "scan_count": 0, "scan_indices": [], "scan_previews": [], "scan_zoomify_paths": [], "has_scans": false}