{"typ záznamu": "Archiválie", "signatura": "I 169", "heslo": "Praha-Karlín - dům čp. 460", "druh": "pozitiv", "obsah": "Pohled detail fasády školy (dům čp. 460) na Lyčkově náměstí v Karlíně (dříve Riegrovy sady) - sgrafita.", "autor": "Alexander, Antonín (1892-působnost do 1948)", "datace": "3.10.1935", "zobrazeno": "150x", "xid": "A1187B99B67611DF820F00166F1163D4", "rejstříkové záznamy": [{"typ": "Dílo", "obsah": "dům čp. 460 (Praha-Karlín); škola"}, {"typ": "Místo", "obsah": "Karlín"}, {"typ": "Místo", "obsah": "Lyčkovo náměstí"}, {"typ": "Osoba", "obsah": "Alexander, Antonín (1892-působnost do 1948)"}], "scan_count": 0, "scan_indices": [], "scan_previews": [], "scan_zoomify_paths": [], "has_scans": false}