{"typ záznamu": "Archiválie", "signatura": "XII 867", "heslo": "Praha-Hradčany - vojenský hřbitov", "druh": "negativ", "obsah": "Pohled na pomník 28 pruských dělostřelců na dělostřeleckém vojenském hřbitově na Hradčanech.", "autor": "Eckert, Jindřich (1833-1905)", "datace": "kol.1900", "zobrazeno": "97x", "xid": "A118845FB67611DF820F00166F1163D4", "rejstříkové záznamy": [{"typ": "Dílo", "obsah": "pomník 28 pruských dělostřelců (Praha-Hradčany)"}, {"typ": "Dílo", "obsah": "vojenský hřbitov (Praha-Hradčany)"}, {"typ": "Místo", "obsah": "Hradčany"}, {"typ": "Osoba", "obsah": "Eckert, Jindřich (1833-1905)"}, {"typ": "Věc. objekt", "obsah": "hřbitovy (areály)"}], "scan_count": 0, "scan_indices": [], "scan_previews": [], "scan_zoomify_paths": [], "has_scans": false}