{"typ záznamu": "Archiválie", "signatura": "V 54/6 d", "heslo": "Praha - pomník M. Jana Husa", "druh": "pozitiv", "obsah": "Odlévání sádrového modelu pomníku M. Jana Husa v ateliéru.", "datace": "[1856-2014]", "poznámka": "Datace neznámá. Za účelem vyhledávání byla nastavena na časový rozsah celé sbírky.", "zobrazeno": "36x", "xid": "A11874BBB67611DF820F00166F1163D4", "rejstříkové záznamy": [{"typ": "Dílo", "obsah": "pomník M. Jana Husa na Staroměstském náměstí (Praha-Staré Město)"}], "scan_count": 0, "scan_indices": [], "scan_previews": [], "scan_zoomify_paths": [], "has_scans": false}