{"typ záznamu": "Archiválie", "signatura": "VI 31/3 e", "heslo": "Praha-Nové Město - kostel sv. Cyrila a Metoděje", "druh": "pozitiv", "obsah": "Celkový pohled na kostel sv. Cyrila a Metoděje (dříve kostel sv. Karla Boromejského) v Resslově ulici na Novém Městě od jihu.", "autor": "Eckert, Jindřich (1833-1905)", "datace": "kol.1898", "zobrazeno": "43x", "xid": "A11887F8B67611DF820F00166F1163D4", "rejstříkové záznamy": [{"typ": "Dílo", "obsah": "kostel svatých Cyrila a Metoděje (Nové Město, Praha, Česko : kostel : 1730-)"}, {"typ": "Místo", "obsah": "Nové Město"}, {"typ": "Místo", "obsah": "Resslova ulice"}, {"typ": "Osoba", "obsah": "Eckert, Jindřich (1833-1905)"}], "scan_count": 0, "scan_indices": [], "scan_previews": [], "scan_zoomify_paths": [], "has_scans": false}