{"typ záznamu": "Archiválie", "signatura": "I 9063", "heslo": "Praha-Hostivař - dům čp. 674", "druh": "pohlednice", "obsah": "Pohled na dům čp. 674 v ulici U Branek v Hostivaři (Švehlova sokolovna).", "datace": "před 1956", "zobrazeno": "79x", "xid": "A1187629B67611DF820F00166F1163D4", "rejstříkové záznamy": [{"typ": "Dílo", "obsah": "dům čp. 674 (Praha-Hostivař); sokolovna"}, {"typ": "Místo", "obsah": "Hostivař"}, {"typ": "Místo", "obsah": "ulice U Branek"}], "scan_count": 0, "scan_indices": [], "scan_previews": [], "scan_zoomify_paths": [], "has_scans": false}