{"typ záznamu": "Archiválie", "signatura": "I 365", "heslo": "Praha-Nové Město - Truhlářská ulice", "druh": "pozitiv", "obsah": "Průhled Truhlářskou ulicí s domy čp. 1130, 1121 (zleva), 1098 (vpravo) na Novém Městě.", "autor": "Alexander, Antonín (1892-působnost do 1948)", "datace": "24.4.1927", "zobrazeno": "77x", "xid": "A1186A81B67611DF820F00166F1163D4", "rejstříkové záznamy": [{"typ": "Dílo", "obsah": "dům čp. 1098 (Praha-Nové Město)"}, {"typ": "Dílo", "obsah": "dům čp. 1121 (Praha-Nové Město)"}, {"typ": "Dílo", "obsah": "dům čp. 1130 (Praha-Nové Město)"}, {"typ": "Místo", "obsah": "Nové Město"}, {"typ": "Místo", "obsah": "Truhlářská ulice"}, {"typ": "Osoba", "obsah": "Alexander, Antonín (1892-působnost do 1948)"}, {"typ": "Věc. objekt", "obsah": "plakáty"}], "scan_count": 0, "scan_indices": [], "scan_previews": [], "scan_zoomify_paths": [], "has_scans": false}