{"typ záznamu": "Archiválie", "signatura": "I 1711", "heslo": "Havel, Václav - portrét", "druh": "pozitiv", "obsah": "Portrét Václava Havla.", "autor": "Josek, Petr", "datace": "15.12.1989", "zobrazeno": "67x", "xid": "A1187EA2B67611DF820F00166F1163D4", "rejstříkové záznamy": [{"typ": "Osoba", "obsah": "Havel, Václav, Mgr. dr. h. c. mult. (prezident : 1936-2011)"}, {"typ": "Osoba", "obsah": "Josek, Petr"}], "scan_count": 0, "scan_indices": [], "scan_previews": [], "scan_zoomify_paths": [], "has_scans": false}