{"typ záznamu": "Archiválie", "signatura": "VI 35/5 a", "heslo": "Praha-Nové Město - kostel P. Marie Sněžné", "druh": "kresba tužkou", "obsah": "Pohled na gotický tympanon u kostela P. Marie Sněžné na Novém Městě.", "poznámka": "Datace neznámá. Za účelem vyhledávání byla nastavena na časový rozsah celé sbírky.", "zobrazeno": "31x", "xid": "A1186B4EB67611DF820F00166F1163D4", "rejstříkové záznamy": [{"typ": "Dílo", "obsah": "kostel P. Marie Sněžné (Praha-Nové Město)"}, {"typ": "Místo", "obsah": "Jungmannovo náměstí"}, {"typ": "Místo", "obsah": "Nové Město"}], "scan_count": 0, "scan_indices": [], "scan_previews": [], "scan_zoomify_paths": [], "has_scans": false}