{"typ záznamu": "Archiválie", "signatura": "VI 61/4", "heslo": "Praha-Staré Město - Staroměstské náměstí", "druh": "pozitiv", "obsah": "Pohled na Staroměstské náměstí od Malého náměstí k východu. Zleva domy čp. 4, 3, jižní část Staroměstské radnice (dům čp. 1 na Starém Městě) s věží, orlojem a portálem, domy čp. 604, 603, nad nimi kostel P. Marie před Týnem. Vpravo část domu čp. 460 na Starém Městě.", "autor": "Fridrich, František (1829-1892)", "datace": "1880", "zobrazeno": "101x", "xid": "A14CE9BDB67611DF820F00166F1163D4", "rejstříkové záznamy": [{"typ": "Dílo", "obsah": "dům čp. 3 (Praha-Staré Město); U Minuty"}, {"typ": "Dílo", "obsah": "dům čp. 4 (Praha-Staré Město)"}, {"typ": "Dílo", "obsah": "dům čp. 460 (Praha-Staré Město)"}, {"typ": "Dílo", "obsah": "dům čp. 603 (Praha-Staré Město)"}, {"typ": "Dílo", "obsah": "dům čp. 604 (Praha-Staré Město)"}, {"typ": "Dílo", "obsah": "kostel Panny Marie před Týnem (Staré Město, Praha, Česko : kostel)"}, {"typ": "Dílo", "obsah": "Staroměstská radnice (Staroměstské náměstí, Praha, Česko)"}, {"typ": "Dílo", "obsah": "Staroměstský orloj (Mikuláš z Kadaně : Staré Město, Praha, Česko : asi 1410-)"}, {"typ": "Místo", "obsah": "Staré Město"}, {"typ": "Místo", "obsah": "Staroměstské náměstí"}, {"typ": "Osoba", "obsah": "Fridrich, František (1829-1892)"}], "scan_count": 0, "scan_indices": [], "scan_previews": [], "scan_zoomify_paths": [], "has_scans": false}