{"typ záznamu": "Archiválie", "signatura": "VI 12/6 b", "heslo": "Praha-Nové Město - Podskalí", "druh": "pozitiv", "obsah": "Pohled na vltavský břeh s domy v Podskalí. V pozadí vlevo na skále Vyšehradská pevnost.", "autor": "Fridrich, František (1829-1892)", "datace": "kol.1870", "zobrazeno": "140x", "xid": "A14CE8E4B67611DF820F00166F1163D4", "rejstříkové záznamy": [{"typ": "Místo", "obsah": "Nové Město"}, {"typ": "Místo", "obsah": "Podskalí"}, {"typ": "Místo", "obsah": "Vyšehradská skála"}, {"typ": "Osoba", "obsah": "Fridrich, František (1829-1892)"}], "scan_count": 0, "scan_indices": [], "scan_previews": [], "scan_zoomify_paths": [], "has_scans": false}