{"typ záznamu": "Archiválie", "signatura": "VI 8/11", "heslo": "Praha-Malá Strana - dům čp. 128", "druh": "pozitiv", "obsah": "Pohled na původní dům čp. 128 na Malé Straně \"letní dům Jezuitů\" v Jezuitské zahradě na Malé Straně při úpravě terénu pro stavbu Strakovy akademie. V pozadí břeh s Rudolfinem a panorama Starého Města.", "autor": "Eckert, Jindřich (1833-1905)", "datace": "kol.1893", "zobrazeno": "50x", "xid": "A14CE7D1B67611DF820F00166F1163D4", "rejstříkové záznamy": [{"typ": "Dílo", "obsah": "dům čp. 128 (Malá Strana, Praha, Česko : stavba : 1897-)"}, {"typ": "Dílo", "obsah": "dům čp. 128 (Praha-Malá Strana)"}, {"typ": "Místo", "obsah": "Jezuitská zahrada (Praha-Malá Strana)"}, {"typ": "Místo", "obsah": "Malá Strana"}, {"typ": "Osoba", "obsah": "Eckert, Jindřich (1833-1905)"}], "scan_count": 0, "scan_indices": [], "scan_previews": [], "scan_zoomify_paths": [], "has_scans": false}