{"typ záznamu": "Archiválie", "signatura": "VI 61/12", "heslo": "Praha-Nové Město - dům čp. 223", "druh": "pozitiv", "obsah": "Pohled na Národní divadlo (dům čp. 223 na Novém Městě) z mostu císaře Františka I. (Legií). Vlevo část domu čp. 1012 na Starém Městě (kavárna Slavia) a Národní třída.", "autor": "Eckert-ateliér", "datace": "kol.1910", "zobrazeno": "88x", "xid": "A14CEA42B67611DF820F00166F1163D4", "rejstříkové záznamy": [{"typ": "Dílo", "obsah": "dům čp. 1012 (Praha-Staré Město)"}, {"typ": "Dílo", "obsah": "most Legií (Praha, Česko : most : 1901-)"}, {"typ": "Dílo", "obsah": "Národní divadlo (Nové Město, Praha, Česko : divadlo : 1881-)"}, {"typ": "Místo", "obsah": "Národní třída"}, {"typ": "Místo", "obsah": "Nové Město"}, {"typ": "Místo", "obsah": "Staré Město"}, {"typ": "Osoba", "obsah": "Eckert-ateliér"}], "scan_count": 0, "scan_indices": [], "scan_previews": [], "scan_zoomify_paths": [], "has_scans": false}