{"typ záznamu": "Archiválie", "signatura": "VI 53/15", "heslo": "Praha-Malá Strana - dům čp. 84", "druh": "pozitiv", "obsah": "Pohled na dům čp. 84 (\"U Tří měsíců\") při začátku demolice. Vpravo za dřevěnou lávkou přes Čertovku část domu čp. 515. Vlevo pohled do ulice U Lužického semináře s částí domu čp. 83 na Malé Straně.", "autor": "Eckert-ateliér", "datace": "20.5.1905", "zobrazeno": "47x", "xid": "A14CEA85B67611DF820F00166F1163D4", "rejstříkové záznamy": [{"typ": "Dílo", "obsah": "dům čp. 515 (Praha-Malá Strana)"}, {"typ": "Dílo", "obsah": "dům čp. 83 (Praha-Malá Strana)"}, {"typ": "Dílo", "obsah": "dům čp. 84 (Praha-Malá Strana)"}, {"typ": "Místo", "obsah": "Malá Strana"}, {"typ": "Místo", "obsah": "U Lužického semináře"}, {"typ": "Osoba", "obsah": "Eckert-ateliér"}, {"typ": "Věc. objekt", "obsah": "Asanace"}], "scan_count": 0, "scan_indices": [], "scan_previews": [], "scan_zoomify_paths": [], "has_scans": false}