{"typ záznamu": "Archiválie", "signatura": "I 8867", "heslo": "Praha - Karlův most", "druh": "pozitiv", "obsah": "Oprava jednoho z pilířů Karlova mostu.", "autor": "Roleček, Jiří (působnost od 1950-působnost do 1970)", "datace": "1957", "zobrazeno": "54x", "xid": "A14CE0AFB67611DF820F00166F1163D4", "rejstříkové záznamy": [{"typ": "Dílo", "obsah": "Karlův most (Praha, Česko : stavba : 1357-)"}, {"typ": "Osoba", "obsah": "Roleček, Jiří (působnost od 1950-působnost do 1970)"}], "scan_count": 0, "scan_indices": [], "scan_previews": [], "scan_zoomify_paths": [], "has_scans": false}