{"typ záznamu": "Archiválie", "signatura": "VI 7/51 c", "heslo": "Praha-Nové Město - Senovážné náměstí", "druh": "pozitiv", "obsah": "Celkový pohled na dům čp. 976 na Senovážném náměstí na Novém Městě.", "datace": "[1856-2014]", "poznámka": "Datace neznámá. Za účelem vyhledávání byla nastavena na časový rozsah celé sbírky.", "zobrazeno": "71x", "xid": "A14CE28BB67611DF820F00166F1163D4", "rejstříkové záznamy": [{"typ": "Dílo", "obsah": "dům čp. 976 (Praha-Nové Město)"}, {"typ": "Místo", "obsah": "Nové Město"}, {"typ": "Místo", "obsah": "Senovážné náměstí"}], "scan_count": 0, "scan_indices": [], "scan_previews": [], "scan_zoomify_paths": [], "has_scans": false}