{"typ záznamu": "Archiválie", "signatura": "V 12/5", "heslo": "Praha-Malá Strana - Malostranské náměstí", "druh": "pozitiv", "obsah": "Pohled na Malostranské náměstí s pomníkem maršála Radeckého. Uprostřed dům čp. 5 na Malé Straně (s nápisem Česká banka).", "datace": "1914", "zobrazeno": "64x", "xid": "D0C52C2F659111E8B6E074D435EEBE90", "rejstříkové záznamy": [{"typ": "Dílo", "obsah": "dům čp. 5 (Praha-Malá Strana)"}, {"typ": "Dílo", "obsah": "Jan Václav Radecký z Radče (Malostranské náměstí, Praha, Česko : pomník : 1858-1919)"}, {"typ": "Místo", "obsah": "Malá Strana"}, {"typ": "Místo", "obsah": "Malostranské náměstí"}, {"typ": "Věc. objekt", "obsah": "Česká banka"}], "scan_count": 0, "scan_indices": [], "scan_previews": [], "scan_zoomify_paths": [], "has_scans": false}