{"typ záznamu": "Archiválie", "signatura": "A 3374", "heslo": "Praha-Malá Chuchle - panorama", "druh": "pozitiv", "obsah": "Pohled ze stráně nad Malou Chuchlí k jihu na zalesněný kopec mezi Chuchlí a Slivencem. Součást panoramatu.", "autor": "Alexander, Antonín (1892-působnost do 1948)", "datace": "17.6.1927", "zobrazeno": "18x", "xid": "D37D2DAE035911E7A51174D435EEBE90", "rejstříkové záznamy": [{"typ": "Osoba", "obsah": "Alexander, Antonín (1892-působnost do 1948)"}], "scan_count": 0, "scan_indices": [], "scan_previews": [], "scan_zoomify_paths": [], "has_scans": false}