{"typ záznamu": "Archiválie", "signatura": "I 11531", "heslo": "Praha-Hradčany - Pražský hrad", "druh": "pozitiv", "obsah": "Celkový pohled na Pražský hrad z Chotkovy silnice.", "autor": "Fridrich, František (1829-1892)", "datace": "kol.1867", "zobrazeno": "128x", "xid": "D79C2E83D6FE11E5A64F74D435EEBE90", "rejstříkové záznamy": [{"typ": "Dílo", "obsah": "Pražský hrad (Hradčany, Praha, Česko : stavba)"}, {"typ": "Místo", "obsah": "Hradčany"}, {"typ": "Místo", "obsah": "Chotkova"}, {"typ": "Osoba", "obsah": "Fridrich, František (1829-1892)"}, {"typ": "Osoba", "obsah": "Maloch, Karel (1858-1933)"}], "scan_count": 0, "scan_indices": [], "scan_previews": [], "scan_zoomify_paths": [], "has_scans": false}