{"typ záznamu": "Archiválie", "signatura": "I 11724", "heslo": "Praha - Vltava - splavnění", "druh": "pozitiv", "obsah": "Pohled na starý Helmovský jez. V pozadí most císaře Františka Josefa I.", "datace": "10.11.1909", "zobrazeno": "50x", "xid": "DBA502564F3A11E6A549000C76270B94", "rejstříkové záznamy": [{"typ": "Dílo", "obsah": "most císaře Františka Josefa I. (Praha, Česko : most : 1868-1947)"}, {"typ": "Místo", "obsah": "Vltava"}, {"typ": "Věc. objekt", "obsah": "jezy (vodní díla)"}], "scan_count": 0, "scan_indices": [], "scan_previews": [], "scan_zoomify_paths": [], "has_scans": false}