{"typ záznamu": "Archiválie", "signatura": "I 9427", "heslo": "Praha-Malešice - kaple sv. Václava", "druh": "pozitiv", "obsah": "Pohled na kapli sv. Václava na Malešickém náměstí v Malešicích.", "datace": "7.6.1958", "zobrazeno": "50x", "xid": "DFE886DD2D1411E0823D00166F1163D4", "rejstříkové záznamy": [{"typ": "Dílo", "obsah": "kaple sv. Václava (Praha-Malešice)"}, {"typ": "Místo", "obsah": "Malešice"}, {"typ": "Místo", "obsah": "Malešické náměstí"}], "scan_count": 0, "scan_indices": [], "scan_previews": [], "scan_zoomify_paths": [], "has_scans": false}