{"typ záznamu": "Archiválie", "signatura": "XI 128", "heslo": "Praha-Malá Strana - věž Mostecká", "druh": "negativ", "obsah": "Pohled na okenní štít na malé Mostecké věži na Malé Straně.", "autor": "Kříženecký, Jan (1868-1921)", "datace": "19.5.1906", "zobrazeno": "26x", "xid": "E5C2EF47A86811E3A595406186009F3A", "rejstříkové záznamy": [{"typ": "Dílo", "obsah": "Malostranské mostecké věže (Praha-Staré Město)"}, {"typ": "Místo", "obsah": "Malá Strana"}, {"typ": "Místo", "obsah": "Mostecká ulice"}, {"typ": "Osoba", "obsah": "Kříženecký, Jan (1868-1921)"}], "scan_count": 0, "scan_indices": [], "scan_previews": [], "scan_zoomify_paths": [], "has_scans": false}