{"typ záznamu": "Archiválie", "signatura": "A 14452", "heslo": "Praha-Bohnice - dům čp. 4", "druh": "pozitiv", "obsah": "Pohled na východní průčelí fary v Bohnicích (dům čp. 4).", "autor": "Alexander, Antonín (1892-působnost do 1948)", "datace": "31.7.1942", "zobrazeno": "24x", "xid": "e68bae4a99854c26ba61b80306bac83c", "rejstříkové záznamy": [{"typ": "Dílo", "obsah": "dům čp. 3 (Praha-Bohnice); škola"}, {"typ": "Místo", "obsah": "Bohnice"}, {"typ": "Místo", "obsah": "Bohnická ulice"}, {"typ": "Osoba", "obsah": "Alexander, Antonín (1892-působnost do 1948)"}, {"typ": "Osoba", "obsah": "Balard, Tomáš"}], "scan_count": 0, "scan_indices": [], "scan_previews": [], "scan_zoomify_paths": [], "has_scans": false}