{"typ záznamu": "Archiválie", "signatura": "V 18/3 a", "heslo": "Praha-Dejvice - vykopávky", "druh": "pozitiv", "obsah": "Pohled na archeologické vykopávky v Meilbeckově cihelně v Podbabě - kostrový hrob č. 4 a č. 9.", "datace": "před 1922", "zobrazeno": "77x", "xid": "EBC375248C0711E8A45074D435EEBE90", "rejstříkové záznamy": [{"typ": "Dílo", "obsah": "cihelna (Praha-Dejvice); Meilbeckova"}, {"typ": "Místo", "obsah": "Dejvice"}, {"typ": "Věc. objekt", "obsah": "archeologické vykopávky"}], "scan_count": 0, "scan_indices": [], "scan_previews": [], "scan_zoomify_paths": [], "has_scans": false}