{"typ záznamu": "Archiválie", "signatura": "XI 437", "heslo": "Praha-Nové Město - dům čp. 1962", "druh": "negativ", "obsah": "Celkový pohled na budovu České dětské nemocnice (dům čp. 1962) na Karlově na Novém Městě.", "autor": "Kříženecký, Jan (1868-1921)", "datace": "15.10.1907", "zobrazeno": "26x", "xid": "F456A75ADC2D11E3A3310024BE7CD9AC", "rejstříkové záznamy": [{"typ": "Dílo", "obsah": "dům čp. 1962 (Praha-Nové Město); nemocnice"}, {"typ": "Místo", "obsah": "Karlov (Praha-Nové Město)"}, {"typ": "Místo", "obsah": "Nové Město"}, {"typ": "Osoba", "obsah": "Kříženecký, Jan (1868-1921)"}], "scan_count": 0, "scan_indices": [], "scan_previews": [], "scan_zoomify_paths": [], "has_scans": false}