{"typ záznamu": "Archiválie", "signatura": "VIII 1600", "heslo": "Bechyně", "druh": "negativ", "obsah": "Pohled na město Bechyni se zámkem v pozadí. V popředí Lužnice.", "autor": "Eckert, Jindřich (1833-1905)", "datace": "1898", "zobrazeno": "12x", "xid": "F4AC0023986111E2BF2C525400E46D25", "rejstříkové záznamy": [{"typ": "Dílo", "obsah": "Bechyně (Bechyně, Bechyně, Tábor, Česko : zámek)"}, {"typ": "Místo", "obsah": "Bechyně"}, {"typ": "Místo", "obsah": "Lužnice"}, {"typ": "Osoba", "obsah": "Eckert, Jindřich (1833-1905)"}], "scan_count": 0, "scan_indices": [], "scan_previews": [], "scan_zoomify_paths": [], "has_scans": false}