{"typ záznamu": "Archiválie", "signatura": "A 1684", "heslo": "Praha-Dejvice - panorama", "druh": "pozitiv", "obsah": "Panoramatický pohled na staré Dejvice z novostavby na rohu Podbabské silnice (dnes Jugoslávských partyzánů) a Bučkovy (dnes Rooseveltova) - na stráně Strakovky, Hanspaulky a kostela v Šárce (od jihu směrem k Růžku přes západ k severu). Čtvrtá část čtyřdílného panoramatu.", "autor": "Alexander, Antonín (1892-působnost do 1948)", "datace": "17.5.1925", "zobrazeno": "21x", "xid": "f57da8d10ce54a6484a9e9a3dc334013", "rejstříkové záznamy": [{"typ": "Místo", "obsah": "Dejvice"}, {"typ": "Osoba", "obsah": "Alexander, Antonín (1892-působnost do 1948)"}], "scan_count": 0, "scan_indices": [], "scan_previews": [], "scan_zoomify_paths": [], "has_scans": false}