{"typ záznamu": "Archiválie", "signatura": "I 9632", "heslo": "Praha-Nové Město - dům čp. 852", "druh": "pozitiv", "obsah": "Pohled na dolní část průčelí domu čp. 852 (palác Sylva Taroucca).", "datace": "kol.1942", "zobrazeno": "50x", "xid": "F63B435C1F5111E2AA75406186009F3A", "rejstříkové záznamy": [{"typ": "Dílo", "obsah": "palác Sylva-Taroucca (Nové Město, Praha, Česko : 1752-)"}, {"typ": "Místo", "obsah": "Nové Město"}], "scan_count": 0, "scan_indices": [], "scan_previews": [], "scan_zoomify_paths": [], "has_scans": false}