{"typ záznamu": "Archiválie", "signatura": "A 17010", "heslo": "Praha-Staré Město - Pařížská ulice", "druh": "pozitiv", "obsah": "Pohled z Dvořákova nábřeží do Pařížské ulice. Vlevo vyhořelý dům čp. 883, vpravo čp. 206 na Starém Městě.", "autor": "Alexander, Antonín (1892-působnost do 1948)", "datace": "22.5.1945", "zobrazeno": "49x", "xid": "FE4A3C7E701211E997F474D435EEBE90", "rejstříkové záznamy": [{"typ": "Dílo", "obsah": "dům čp. 206 (Praha-Staré Město)"}, {"typ": "Dílo", "obsah": "dům čp. 883 (Praha-Staré Město)"}, {"typ": "Místo", "obsah": "Pařížská"}, {"typ": "Místo", "obsah": "Staré Město"}, {"typ": "Osoba", "obsah": "Alexander, Antonín (1892-působnost do 1948)"}], "scan_count": 0, "scan_indices": [], "scan_previews": [], "scan_zoomify_paths": [], "has_scans": false}